{
  "categories": [
    {
      "unique_id": "popular",
      "deafult_category":true,
      "locked_for_days": 0,
      "number_of_wallpapers": 30,
      "category_name": {
          "en": "Most Popular",
          "ar": "الأكثر رواجاً",
          "cs": "Nejpopulárnější",
          "da": "Populæreste",
          "de": "Beliebt",
          "es": "Los más populares",
          "fr": "Les plus populaires",
          "hr": "Najpopularnije",
          "hu": "A legnépszerűbbek",
          "in": "Paling Populer",
          "it": "I più popolari",
          "ja": "一番人気",
          "ko": "가장 인기있는",
          "ms": "Paling Popular",
          "nb": "Mest populære",
          "nl": "Populair",
          "pl": "Najpopularniejsze",
          "pt": "Mais Populares",
          "ro": "Cele mai populare",
          "ru": "Самые популярные",
          "sr": "Najpopularnije",
          "sv": "Mest Populära",
          "th": "เป็นที่นิยมที่สุด",
          "tr": "En Popüler",
          "vi": "Phổ biến nhất",
          "zh": "最热门"
      },
      "category_color" : "#3d8324",
      "category_icon" : "https://frfa-rt-category-icons.sfo2.cdn.digitaloceanspaces.com/wp-cat-icons/1-wp-most-popular-ringtones.png",
      "category_version": 1
    },

    {
      "unique_id": "simple",
      "deafult_category":false,
      "locked_for_days": 0,
      "number_of_wallpapers": 80,
      "category_name": {
          "en": "Simple",
          "ar": "Simple",
          "cs": "Jednoduché",
          "da": "Enkel",
          "de": "Einfache",
          "es": "Simples",
          "fr": "Simples",
          "hr": "Jednostavne",
          "hu": "Egyszerű",
          "in": "Sederhana",
          "it": "Semplici",
          "ja": "Simple",
          "ko": "Simple",
          "ms": "Mudah",
          "nb": "Enkle",
          "nl": "Eenvoudige",
          "pl": "Proste",
          "pt": "Simples",
          "ro": "Simple",
          "ru": "Простые",
          "sr": "Jednostavne",
          "sv": "Enkel",
          "th": "Simple",
          "tr": "Sade",
          "vi": "Đơn giản",
          "zh": "Simple"
      },
      "category_color" : "#383838",
      "category_icon" : "https://frfa-rt-category-icons.sfo2.cdn.digitaloceanspaces.com/wp-cat-icons/11-wp-simple.png",
      "category_version": 1
    },        
      
    {
      "unique_id": "abstract",
      "deafult_category":false,
      "locked_for_days": 0,
      "number_of_wallpapers": 30,
      "category_name": {
          "en": "Abstract",
          "ar": "فن تجريدي",
          "cs": "Abstrakt",
          "da": "Abstrakt",
          "de": "Abstrakt",
          "es": "Abstracto",
          "fr": "Abstrait",
          "hr": "Abstraktne",
          "hu": "Absztrakt",
          "in": "Abstrak",
          "it": "Astratti",
          "ja": "概要",
          "ko": "추상",
          "ms": "Abstrak",
          "nb": "Abstrakt",
          "nl": "Abstract",
          "pl": "Abstrakcyjne",
          "pt": "Abstracto",
          "ro": "Abstracte",
          "ru": "Абстрактные",
          "sr": "Abstraktne",
          "sv": "Abstrakta",
          "th": "นามธรรม",
          "tr": "Soyut",
          "vi": "Trừu tượng",
          "zh": "抽象"
      },
      "category_color" : "#3d676b",
      "category_icon" : "https://frfa-rt-category-icons.sfo2.cdn.digitaloceanspaces.com/wp-cat-icons/2-wp-abstract.png",
      "category_version": 1
    },
      
      
    {
      "unique_id": "animal",
      "deafult_category":false,
      "locked_for_days": 0,
      "number_of_wallpapers": 30,
      "category_name": {
          "en": "Animal",
          "ar": "حيوانات",
          "cs": "Zvířata",
          "da": "Dyr",
          "de": "Tier",
          "es": "Animal",
          "fr": "Animaux",
          "hr": "Životinje",
          "hu": "Állatos",
          "in": "Hewan",
          "it": "Animali",
          "ja": "動物",
          "ko": "동물",
          "ms": "Haiwan",
          "nb": "Dyr",
          "nl": "Dieren",
          "pl": "Zwierzęta",
          "pt": "Animais",
          "ro": "Animale",
          "ru": "Животные",
          "sr": "Životinje",
          "sv": "Djur",
          "th": "สัตว์",
          "tr": "Hayvan",
          "vi": "Động vật",
          "zh": "动物"
      },
      "category_color" : "#855a37",
      "category_icon" : "https://frfa-rt-category-icons.sfo2.cdn.digitaloceanspaces.com/wp-cat-icons/3-wp-animals.png",
      "category_version": 1
    },  
      
      
    {
      "unique_id": "architecture",
      "deafult_category":false,
      "locked_for_days": 0,
      "number_of_wallpapers": 30,
      "category_name": {
          "en": "Architecture & Cities",
          "ar": "مدن وفن معماري",
          "cs": "Architektura a města",
          "da": "Arkitekturer & Byer",
          "de": "Architektur & Städte",
          "es": "Ciudades y arquitectura",
          "fr": "Architecture et villes",
          "hr": "Gradovi i arhitektura",
          "hu": "Építészet és városok",
          "in": "Arsitektur & Kota",
          "it": "Architettura e città",
          "ja": "建築物や都市",
          "ko": "건축 및 도시",
          "ms": "Seni bina & Bandar",
          "nb": "Arkitektur og byer",
          "nl": "Steden & Architectuur",
          "pl": "Architektura i Miasta",
          "pt": "Arquitetura e Cidades",
          "ro": "Arhitectură și orașe",
          "ru": "Архитектура и Города",
          "sr": "Gradovi i arhitektura",
          "sv": "Arkitektur & Städer",
          "th": "สถาปัตยกรรมและเมืองต่าง ๆ",
          "tr": "Mimari & Şehirler",
          "vi": "Kiến trúc & Thành phố",
          "zh": "建筑物与城市"
      },
      "category_color" : "#344a5e",
      "category_icon" : "https://frfa-rt-category-icons.sfo2.cdn.digitaloceanspaces.com/wp-cat-icons/4-wp-buildings.png",
      "category_version": 1
    },
      
      
    {
      "unique_id": "funny",
      "deafult_category":false,
      "locked_for_days": 0,
      "number_of_wallpapers": 30,
      "category_name": {
          "en": "Funny",
          "ar": "مضحك",
          "cs": "Zábavné",
          "da": "Sjove",
          "de": "Witzig",
          "es": "Graciosos",
          "fr": "Drôle",
          "hr": "Smiješne",
          "hu": "Vicces",
          "in": "Lucu",
          "it": "Divertenti",
          "ja": "ファニー",
          "ko": "재미",
          "ms": "Lawak",
          "nb": "Humor",
          "nl": "Grappig",
          "pl": "Śmieszne",
          "pt": "Divertido",
          "ro": "Amuzante",
          "ru": "Забавные",
          "sr": "Smešne",
          "sv": "Roliga",
          "th": "ขบขัน",
          "tr": "Eğlenceli",
          "vi": "Hài hước",
          "zh": "搞笑"
      },
      "category_color" : "#e7bf10",
      "category_icon" : "https://frfa-rt-category-icons.sfo2.cdn.digitaloceanspaces.com/wp-cat-icons/5-wp-funny.png",
      "category_version": 1
    },
      
      
    {
      "unique_id": "love",
      "deafult_category":false,
      "number_of_wallpapers": 30,
      "locked_for_days": 0,
      "category_name": {
          "en": "Love & Romance",
          "ar": "رومانسية وحب",
          "cs": "Láska a romance",
          "da": "Kærlighed & Romance",
          "de": "Liebe & Romantik",
          "es": "Amor y romance",
          "fr": "Amour",
          "hr": "Ljubav i romansa",
          "hu": "Szerelmes",
          "in": "Cinta & Romansa",
          "it": "Amore",
          "ja": "ラブ＆ロマンス",
          "ko": "사랑과 로맨스",
          "ms": "Cinta & Romantis",
          "nb": "Kjærlighet og romantikk",
          "nl": "Liefde & Romantiek",
          "pl": "Miłość i Romans",
          "pt": "Amor e Romance",
          "ro": "Dragoste și romantism",
          "ru": "Любовь и Романтика",
          "sr": "Ljubav i romansa",
          "sv": "Kärlek & Romans",
          "th": "ความรักและความโรแมนติก",
          "tr": "Aşk & Romantik",
          "vi": "Tình yêu & Lãng mạn",
          "zh": "爱与浪漫"
      },
      "category_color":"#522424",
      "category_icon" : "https://frfa-rt-category-icons.sfo2.cdn.digitaloceanspaces.com/wp-cat-icons/6-wp-love.png",
      "category_version": 1
    },      
      
      
      
    {
      "unique_id": "music_movies",
      "deafult_category":false,
      "number_of_wallpapers": 30,
      "locked_for_days": 0,
      "category_name": {
          "en": "Music & Movies",
          "ar": "أفلام وموسيقى",
          "cs": "Hudba a filmy",
          "da": "Musik & Film",
          "de": "Musik & Filme",
          "es": "Música y películas",
          "fr": "Musique et films",
          "hr": "Glazba i filmovi",
          "hu": "Zene és filmek",
          "in": "Musik & Film",
          "it": "Musica e film",
          "ja": "音楽や映画",
          "ko": "음악과 영화",
          "ms": "Muzik & Filem",
          "nb": "Musikk og filmer",
          "nl": "Muziek & Film",
          "pl": "Muzyka i Filmy",
          "pt": "Música e Filmes",
          "ro": "Muzică și filme ",
          "ru": "Музыка и фильмы",
          "sr": "Muzika i filmovi",
          "sv": "Musik & Film",
          "th": "ดนตรีและภาพยนตร์",
          "tr": "Müzik & Filmler",
          "vi": "Âm nhạc & Phim",
          "zh": "音乐与电影"
      },
      "category_color":"#5f5f5f",
      "category_icon" : "https://frfa-rt-category-icons.sfo2.cdn.digitaloceanspaces.com/wp-cat-icons/7-wp-movie-music.png",
      "category_version": 1
    },      
      
      
      
    {
      "unique_id": "nature",
      "deafult_category":false,
      "number_of_wallpapers": 30,
      "locked_for_days": 0,
      "category_name": {
          "en": "Nature & Landscape",
          "ar": "جمال الطبيعة",
          "cs": "Příroa a krajiny",
          "da": "Natur & Landskab",
          "de": "Natur & Landschaft",
          "es": "Naturaleza y paisajes",
          "fr": "Nature et paysages",
          "hr": "Priroda i pejzaži",
          "hu": "Természet és tájképek",
          "in": "Alam & Pemandangan",
          "it": "Natura e paesaggi",
          "ja": "自然と風景",
          "ko": "자연과 경치",
          "ms": "Alam Semulajadi & Landskap",
          "nb": "Natur og landskap",
          "nl": "Landschap & Natuur",
          "pl": "Natura i Krajobrazy",
          "pt": "Natureza e Paisagens",
          "ro": "Natură și peisaje",
          "ru": "Природа и пейзажи",
          "sr": "Priroda i pejzaži",
          "sv": "Natur & Landskap",
          "th": "ธรรมชาติและทิวทัศน์",
          "tr": "Doğa & Manzara",
          "vi": "Thiên nhiên & Cảnh quan",
          "zh": "大自然与景观"
      },
      "category_color":"#295322",
      "category_icon" : "https://frfa-rt-category-icons.sfo2.cdn.digitaloceanspaces.com/wp-cat-icons/8-wp-nature.png",
      "category_version": 1
    },      
      
      

    {
      "unique_id": "people",
      "deafult_category":false,
      "number_of_wallpapers": 30,
      "locked_for_days": 2,
      "category_name": {
          "en": "People & Portraits",
          "ar": "لوحات فنية وأشخاص",
          "cs": "Lidé a portréty",
          "da": "Folk & Portrætter",
          "de": "Menschen & Portraits",
          "es": "Gente y retratos",
          "fr": "Personnes et portraits",
          "hr": "Ljudi i portreti",
          "hu": "Emberek és portrék",
          "in": "Orang & Gambar",
          "it": "Persone e ritratti",
          "ja": "人やポートレート",
          "ko": "사람과 추상화",
          "ms": "Manusia & Potret",
          "nb": "Mennesker og portretter",
          "nl": "Mensen & Portretten",
          "pl": "Ludzie i Portrety",
          "pt": "Pessoas e Retratos",
          "ro": "Oameni și portrete",
          "ru": "Люди и Портреты",
          "sr": "Ljudi i portreti",
          "sv": "Människor & Porträtt",
          "th": "ผู้คนและภาพบุคคล",
          "tr": "Portre",
          "vi": "Con người & Chân dung",
          "zh": "人物与肖像"
      },
      "category_color":"#e77238",
      "category_icon" : "https://frfa-rt-category-icons.sfo2.cdn.digitaloceanspaces.com/wp-cat-icons/9-wp-people-portraits.png",
      "category_version": 1
    },      
      
       
      
    {
      "unique_id": "spiritual",
      "deafult_category":false,
      "number_of_wallpapers": 30,
      "locked_for_days": 6,
      "category_name": {
          "en": "Religious & Spiritual",
          "ar": "روحانية ودينية",
          "cs": "Náboženské a duchovní",
          "da": "Religiøse & Spirituelle",
          "de": "Religiös & Spirituell",
          "es": "Religión y espiritualidad",
          "fr": "Religieux et spirituel",
          "hr": "Religiozne i duhovne",
          "hu": "Vallásos és spirituális",
          "in": "Religius & Spiritual",
          "it": "Religiosi e spirituali",
          "ja": "宗教やスピリチュアル",
          "ko": "종교와 영혼",
          "ms": "Agama & Kerohanian",
          "nb": "Religiøst og åndelig",
          "nl": "Religie & Spiritualiteit",
          "pl": "Religijne i Duchowe",
          "pt": "Religião e Espiritual",
          "ro": "Religioase și spirituale",
          "ru": "Религиозные и духовные",
          "sr": "Religiozne i duhovne",
          "sv": "Religiösa & Spirituella",
          "th": "ศาสนาและจิตวิญญาณ",
          "tr": "Dini & Ruhsal",
          "vi": "Tôn giáo & Tâm linh",
          "zh": "宗教与灵性"
      },
      "category_color":"#348ab7",
      "category_icon" : "https://frfa-rt-category-icons.sfo2.cdn.digitaloceanspaces.com/wp-cat-icons/10-wp-spiritual.png",
      "category_version": 1
    }
      
  ]
}